__init__.py
ae_pvalues.py
demo/simple_arithmetic.ipynb
demo/.ipynb_checkpoints/mnist_example-checkpoint.ipynb
ae_pvalues-1.0.dist-info/METADATA
ae_pvalues-1.0.dist-info/WHEEL
ae_pvalues-1.0.dist-info/entry_points.txt
ae_pvalues-1.0.dist-info/licenses/LICENSE.txt
ae_pvalues-1.0.dist-info/RECORD
