Metadata-Version: 2.1
Name: ae-pvalues
Version: 1.0
Summary: A tool to explain anomalies identified by an auto-encoder based on pvalues 
Project-URL: Homepage, https://gitlab.inria.fr/mlanvin/ae-pvalues
Project-URL: Bug Tracker, https://gitlab.inria.fr/mlanvin/ae-pvalues
Author-email: Maxime LANVIN <maxime.lanvin@inria.fr>
License-File: LICENSE.txt
Classifier: License :: OSI Approved :: MIT License
Classifier: Operating System :: OS Independent
Classifier: Programming Language :: Python :: 3
Requires-Python: >=3.9
Requires-Dist: numpy
Requires-Dist: psutil
Requires-Dist: scikit-learn
Requires-Dist: scipy
Requires-Dist: tqdm
